dsfx/__init__.py
dsfx/dsfx.py
dsfx/exceptions.py
dsfx-0.3.dist-info/LICENSE
dsfx-0.3.dist-info/METADATA
dsfx-0.3.dist-info/WHEEL
dsfx-0.3.dist-info/entry_points.txt
dsfx-0.3.dist-info/top_level.txt
dsfx-0.3.dist-info/RECORD
