Metadata-Version: 2.1
Name: dsfx
Version: 0.3
Summary: create installer packages
Author-email: Soumyo Deep Gupta <deep.main.ac@gmail.com>
Maintainer-email: Soumyo Deep Gupta <deep.main.ac@gmail.com>
License: MIT License
Project-URL: GitHub, https://github.com/d33pster/dsfx
Project-URL: Issues, https://github.com/d33pster/dsfx/issues
Project-URL: Documentation, https://d33pster.github.io/dsfx/
Keywords: d33pster,pymakeself,makeself,makesfx,dsfx,pythonsfx
Classifier: Development Status :: 4 - Beta
Classifier: Intended Audience :: Developers
Classifier: Topic :: Software Development :: Build Tools
Classifier: Programming Language :: Python :: 3.9
Classifier: Programming Language :: Python :: 3.10
Classifier: Programming Language :: Python :: 3.11
Classifier: Programming Language :: Python :: 3.12
Classifier: License :: OSI Approved :: MIT License
Classifier: Operating System :: OS Independent
Requires-Python: >=3.9
License-File: LICENSE
Requires-Dist: optioner >=1.5.2
Requires-Dist: colorama
Requires-Dist: argparse
Requires-Dist: cryptography
Requires-Dist: pyinstaller
